whatsapp/__init__.py
whatsapp/constants.py
whatsapp/errors.py
whatsapp/async_ext/_buttons.py
whatsapp/async_ext/_media.py
whatsapp/async_ext/_message.py
whatsapp/async_ext/_property.py
whatsapp/async_ext/_send_media.py
whatsapp/async_ext/_send_others.py
whatsapp/async_ext/_static.py
whatsapp/ext/_buttons.py
whatsapp/ext/_media.py
whatsapp/ext/_message.py
whatsapp/ext/_property.py
whatsapp/ext/_send_media.py
whatsapp/ext/_send_others.py
whatsapp/ext/_static.py
whatsapp_python-4.3.0.dist-info/METADATA
whatsapp_python-4.3.0.dist-info/WHEEL
whatsapp_python-4.3.0.dist-info/licenses/LICENSE
whatsapp_python-4.3.0.dist-info/RECORD
