Metadata-Version: 2.3
Name: whatsapp-python
Version: 4.3.0
Summary: Open source Python wrapper for the WhatsApp Cloud API
Project-URL: Homepage, https://github.com/filipporomani/whatsapp-python
Project-URL: Docs, https://github.com/filipporomani/whatsapp-python/wiki
Project-URL: Issues Reporting, https://github.com/filipporomani/whatsapp-python/issues
Project-URL: Download, https://github.com/filipporomani/whatsapp-python/releases/latest
Project-URL: Changelog, https://github.com/filipporomani/whatsapp-python/releases
Author-email: Filippo Romani <mail@filipporomani.it>
Classifier: Development Status :: 4 - Beta
Classifier: Intended Audience :: Customer Service
Classifier: Intended Audience :: Developers
Classifier: Intended Audience :: Education
Classifier: Intended Audience :: Telecommunications Industry
Classifier: License :: OSI Approved :: GNU Affero General Public License v3
Classifier: Programming Language :: Python :: 3.10
Classifier: Programming Language :: Python :: 3.11
Classifier: Programming Language :: Python :: 3.12
Classifier: Programming Language :: Python :: 3.13
Classifier: Programming Language :: Python :: 3.14
Classifier: Topic :: Communications :: Chat
Classifier: Topic :: Communications :: Telephony
Classifier: Topic :: Internet :: WWW/HTTP :: HTTP Servers
Classifier: Topic :: Internet :: WWW/HTTP :: WSGI :: Application
Classifier: Topic :: Software Development :: Build Tools
Classifier: Topic :: Software Development :: Libraries :: Python Modules
Requires-Python: >=3.10
Requires-Dist: aiohttp
Requires-Dist: asyncio
Requires-Dist: beautifulsoup4
Requires-Dist: fastapi
Requires-Dist: python-dotenv
Requires-Dist: requests-toolbelt
Requires-Dist: uvicorn
